aeppl/__init__.py
aeppl/_version.py
aeppl/abstract.py
aeppl/censoring.py
aeppl/cumsum.py
aeppl/dists.py
aeppl/joint_logprob.py
aeppl/logprob.py
aeppl/mixture.py
aeppl/printing.py
aeppl/rewriting.py
aeppl/scan.py
aeppl/tensor.py
aeppl/transforms.py
aeppl/utils.py
aeppl_nightly-0.0.40.dist-info/LICENSE
aeppl_nightly-0.0.40.dist-info/METADATA
aeppl_nightly-0.0.40.dist-info/WHEEL
aeppl_nightly-0.0.40.dist-info/top_level.txt
aeppl_nightly-0.0.40.dist-info/RECORD
